setup.py
quartet/__init__.py
quartet.egg-info/PKG-INFO
quartet.egg-info/SOURCES.txt
quartet.egg-info/dependency_links.txt
quartet.egg-info/not-zip-safe
quartet.egg-info/top_level.txt