Metadata-Version: 1.0
Name: quartet
Version: 0.0.1
Summary: A Python library for playing with strings
Home-page: https://github.com/hexrcs/quartet
Author: Xiaoru Li
Author-email: hello@xiaoru.li
License: MIT
Platform: UNKNOWN
